yato/JSONManip.py
yato/__init__.py
yato/actions.py
yato/conftest.py
yato/get.py
yato/test_actions.py
yato/yato.py
yato-1.3.0.dist-info/LICENSE
yato-1.3.0.dist-info/METADATA
yato-1.3.0.dist-info/WHEEL
yato-1.3.0.dist-info/entry_points.txt
yato-1.3.0.dist-info/top_level.txt
yato-1.3.0.dist-info/RECORD
