Metadata-Version: 2.1
Name: yato
Version: 1.3.0
Summary: yato - Yet another Todo app, a cli program for TODO lists
Home-page: https://github.com/TheArchons/yato
Author: TheArchons
Author-email: alexli9138@gmail.com
License: MIT
Keywords: yato,todo,list,tasks
Platform: UNKNOWN
License-File: LICENSE
Requires-Dist: termcolor
